qtrio/__init__.py
qtrio/__main__.py
qtrio/_cli.py
qtrio/_core.py
qtrio/_exceptions.py
qtrio/_python.py
qtrio/_qt.py
qtrio/_util.py
qtrio/_version.py
qtrio/dialogs.py
qtrio/py.typed
qtrio/qt.py
qtrio/_tests/__init__.py
qtrio/_tests/conftest.py
qtrio/_tests/helpers.py
qtrio/_tests/test_cli.py
qtrio/_tests/test_core.py
qtrio/_tests/test_dialogs.py
qtrio/_tests/test_exceptions.py
qtrio/_tests/test_pytest.py
qtrio/_tests/test_python.py
qtrio/_tests/test_qt.py
qtrio/_tests/test_qtrio.py
qtrio/_tests/examples/__init__.py
qtrio/_tests/examples/test_buildingrespect.py
qtrio/_tests/examples/test_crossingpaths.py
qtrio/_tests/examples/test_download.py
qtrio/_tests/examples/test_emissions.py
qtrio/_tests/examples/readme/__init__.py
qtrio/_tests/examples/readme/test_console.py
qtrio/_tests/examples/readme/test_qt.py
qtrio/_tests/examples/readme/test_qtrio.py
qtrio/examples/__init__.py
qtrio/examples/buildingrespect.py
qtrio/examples/crossingpaths.py
qtrio/examples/download.py
qtrio/examples/emissions.py
qtrio/examples/readme/__init__.py
qtrio/examples/readme/console.py
qtrio/examples/readme/qt.py
qtrio/examples/readme/qtrio_example.py
qtrio-0.7.0.dist-info/LICENSE
qtrio-0.7.0.dist-info/LICENSE.APACHE2
qtrio-0.7.0.dist-info/LICENSE.MIT
qtrio-0.7.0.dist-info/METADATA
qtrio-0.7.0.dist-info/WHEEL
qtrio-0.7.0.dist-info/entry_points.txt
qtrio-0.7.0.dist-info/top_level.txt
qtrio-0.7.0.dist-info/RECORD
