Metadata-Version: 2.1
Name: qtrio
Version: 0.7.0
Summary: a library bringing Qt GUIs together with ``async`` and ``await`` via Trio
Home-page: https://github.com/altendky/qtrio
Author: Kyle Altendorf
Author-email: sda@fstab.net
License: MIT -or- Apache License 2.0
Project-URL: Documentation, https://qtrio.readthedocs.io/
Project-URL: Chat, https://gitter.im/python-trio/general
Project-URL: Forum, https://trio.discourse.group/
Project-URL: Issues, https://github.com/altendky/qtrio/issues
Project-URL: Repository, https://github.com/altendky/qtrio
Project-URL: Tests, https://github.com/altendky/qtrio/actions?query=branch%3Amain
Project-URL: Coverage, https://codecov.io/gh/altendky/qtrio
Project-URL: Distribution, https://pypi.org/project/qtrio
Keywords: async,io,Trio,GUI,Qt,PyQt5,PySide2
Classifier: License :: OSI Approved :: MIT License
Classifier: License :: OSI Approved :: Apache Software License
Classifier: Framework :: Trio
Classifier: Operating System :: POSIX :: Linux
Classifier: Operating System :: MacOS :: MacOS X
Classifier: Operating System :: Microsoft :: Windows
Classifier: Programming Language :: Python :: 3 :: Only
Classifier: Programming Language :: Python :: 3.7
Classifier: Programming Language :: Python :: 3.8
Classifier: Programming Language :: Python :: 3.9
Classifier: Programming Language :: Python :: 3.10
Classifier: Programming Language :: Python :: 3.11
Classifier: Programming Language :: Python :: Implementation :: CPython
Classifier: Development Status :: 3 - Alpha
Classifier: Intended Audience :: Developers
Classifier: Topic :: Software Development :: User Interfaces
Requires-Python: >=3.7
License-File: LICENSE
License-File: LICENSE.APACHE2
License-File: LICENSE.MIT
Requires-Dist: async-generator
Requires-Dist: attrs
Requires-Dist: decorator
Requires-Dist: outcome
Requires-Dist: qts (~=0.3.0)
Requires-Dist: trio (>=0.17)
Requires-Dist: trio-typing (~=0.8.0)
Requires-Dist: typing-extensions ; python_version < "3.8"
Provides-Extra: cli
Requires-Dist: click (~=8.1) ; extra == 'cli'
Provides-Extra: examples
Requires-Dist: click (~=8.1) ; extra == 'examples'
Requires-Dist: httpcore (~=0.16) ; extra == 'examples'
Requires-Dist: httpx (~=0.23) ; extra == 'examples'
Requires-Dist: hyperlink (~=21.0.0) ; extra == 'examples'
Provides-Extra: p_checks
Requires-Dist: black (==22.10.0) ; extra == 'p_checks'
Requires-Dist: check-manifest (~=0.46.0) ; extra == 'p_checks'
Requires-Dist: flake8 (~=3.8) ; extra == 'p_checks'
Requires-Dist: mypy (==0.991) ; extra == 'p_checks'
Requires-Dist: pytest (~=7.2) ; extra == 'p_checks'
Requires-Dist: quart-trio (~=0.10.0) ; extra == 'p_checks'
Requires-Dist: quart (~=0.18.3) ; extra == 'p_checks'
Requires-Dist: towncrier (>=21.3.0) ; extra == 'p_checks'
Requires-Dist: click (~=8.1) ; extra == 'p_checks'
Requires-Dist: httpcore (~=0.16) ; extra == 'p_checks'
Requires-Dist: httpx (~=0.23) ; extra == 'p_checks'
Requires-Dist: hyperlink (~=21.0.0) ; extra == 'p_checks'
Provides-Extra: p_docs
Requires-Dist: sphinx (>=4.0.0b2,~=5.1) ; extra == 'p_docs'
Requires-Dist: sphinx-autodoc-typehints (~=1.11) ; extra == 'p_docs'
Requires-Dist: sphinx-qt-documentation (~=0.4.0) ; extra == 'p_docs'
Requires-Dist: sphinx-rtd-theme (~=1.0) ; extra == 'p_docs'
Requires-Dist: sphinxcontrib-trio (~=1.1) ; extra == 'p_docs'
Requires-Dist: towncrier (>=21.3.0) ; extra == 'p_docs'
Provides-Extra: p_tests
Requires-Dist: click (~=8.1) ; extra == 'p_tests'
Requires-Dist: httpcore (~=0.16) ; extra == 'p_tests'
Requires-Dist: httpx (~=0.23) ; extra == 'p_tests'
Requires-Dist: hyperlink (~=21.0.0) ; extra == 'p_tests'
Requires-Dist: coverage (~=6.5) ; extra == 'p_tests'
Requires-Dist: pytest (~=7.2) ; extra == 'p_tests'
Requires-Dist: pytest-cov (~=4.0) ; extra == 'p_tests'
Requires-Dist: pytest-faulthandler (~=2.0) ; extra == 'p_tests'
Requires-Dist: pytest-qt (~=4.2) ; extra == 'p_tests'
Requires-Dist: pytest-trio (>=0.7.0) ; extra == 'p_tests'
Requires-Dist: pytest-xdist[psutil] (~=2.2) ; extra == 'p_tests'
Requires-Dist: quart-trio (~=0.10.0) ; extra == 'p_tests'
Requires-Dist: quart (~=0.18.3) ; extra == 'p_tests'
Requires-Dist: pytest-xvfb (~=2.0) ; (sys_platform == "linux") and extra == 'p_tests'
Provides-Extra: pyqt5
Requires-Dist: pyqt5 (~=5.15.1) ; extra == 'pyqt5'
Requires-Dist: pyqt5-stubs (~=5.15.2) ; extra == 'pyqt5'
Provides-Extra: pyside2
Requires-Dist: pyside2 (!=5.15.2,!=5.15.2.1,~=5.15) ; extra == 'pyside2'
Provides-Extra: s_pytest
Requires-Dist: pytest (~=7.2) ; extra == 's_pytest'
Provides-Extra: s_pytest_trio
Requires-Dist: pytest-trio (>=0.7.0) ; extra == 's_pytest_trio'
Provides-Extra: s_quart_trio
Requires-Dist: quart-trio (~=0.10.0) ; extra == 's_quart_trio'
Requires-Dist: quart (~=0.18.3) ; extra == 's_quart_trio'
Provides-Extra: s_towncrier
Requires-Dist: towncrier (>=21.3.0) ; extra == 's_towncrier'
Provides-Extra: testing
Requires-Dist: pytest-trio (>=0.7.0) ; extra == 'testing'
